roself/__init__.py
roself/cli.py
roself-1.0.0.dist-info/LICENSE
roself-1.0.0.dist-info/METADATA
roself-1.0.0.dist-info/WHEEL
roself-1.0.0.dist-info/entry_points.txt
roself-1.0.0.dist-info/top_level.txt
roself-1.0.0.dist-info/RECORD
